<?xml version="1.0" encoding="UTF-8"?>
<metadata xml:lang="en"><Esri><CreaDate>20250711</CreaDate><CreaTime>13194000</CreaTime><ArcGISFormat>1.0</ArcGISFormat><SyncOnce>TRUE</SyncOnce><ModDate>20250711</ModDate><ModTime>131940</ModTime></Esri><toolbox name="Quick PDF Export Toolbox" alias=""><arcToolboxHelpPath>e:\sw_nt\arcgis\Resources\Help\gp</arcToolboxHelpPath><toolsets/></toolbox><dataIdInfo><idCitation><resTitle>Quick PDF Export Toolbox</resTitle></idCitation></dataIdInfo><distInfo><distributor><distorFormat><formatName>ArcToolbox Toolbox</formatName></distorFormat></distributor></distInfo></metadata>
